ftopsis_class_cin/__init__.py
ftopsis_class_cin/classes/trapezoidal_core.py
ftopsis_class_cin/classes/triangular_core.py
ftopsis_class_cin/classes/utils/invert_matrix.py
ftopsis_class_cin/decision.py
ftopsis_class_cin/main.py
ftopsis_class_cin/utils/format_output.py
ftopsis_class_cin/utils/invert_matrix.py
ftopsis_class_cin-0.1.1.dist-info/METADATA
ftopsis_class_cin-0.1.1.dist-info/WHEEL
ftopsis_class_cin-0.1.1.dist-info/RECORD
