Metadata-Version: 2.3
Name: ftopsis_class_cin
Version: 0.1.1
Summary: Biblioteca Ftopsis Class
License: MIT
Author: José Ronaldo, Luiz Henrique
Requires-Python: >=3.10
Classifier: License :: OSI Approved :: MIT License
Classifier: Programming Language :: Python :: 3
Classifier: Programming Language :: Python :: 3.10
Classifier: Programming Language :: Python :: 3.11
Classifier: Programming Language :: Python :: 3.12
Classifier: Programming Language :: Python :: 3.13
Requires-Dist: numpy (==1.26.4)
Requires-Dist: pandas (==2.2.2)
